hikload/__init__.py
hikload/__main__.py
hikload/download.py
hikload/ui.py
hikload/hikvisionapi/RTSPutils.py
hikload/hikvisionapi/_ContentMgmt.py
hikload/hikvisionapi/_Streaming.py
hikload/hikvisionapi/_System.py
hikload/hikvisionapi/__init__.py
hikload/hikvisionapi/classes.py
hikload/hikvisionapi/utils.py
hikload/uifiles/MainWindow.py
hikload/uifiles/Startup.py
hikload/uifiles/__init__.py
hikload-1.1.4.dist-info/LICENSE
hikload-1.1.4.dist-info/METADATA
hikload-1.1.4.dist-info/WHEEL
hikload-1.1.4.dist-info/entry_points.txt
hikload-1.1.4.dist-info/top_level.txt
hikload-1.1.4.dist-info/RECORD
