Metadata-Version: 2.1
Name: hikload
Version: 1.1.4
Summary: Download videos from a HikVision DVR/NVR
Home-page: https://github.com/Tedyst/HikLoad
Author: Stoica Tedy
Author-email: stoicatedy@gmail.com
License: MIT
Classifier: License :: OSI Approved :: MIT License
Classifier: Programming Language :: Python :: 3
Classifier: Programming Language :: Python :: 3.10
License-File: LICENSE
Requires-Dist: ffmpeg-python (==0.2.0)
Requires-Dist: lxml (==4.9.1)
Requires-Dist: pefile (==2022.5.30)
Requires-Dist: pyqt5 (==5.15.7)
Requires-Dist: pyqt5-qt5 (==5.15.2)
Requires-Dist: pywin32-ctypes (==0.2.0)
Requires-Dist: requests (==2.28.1)
Requires-Dist: tqdm (==4.64.0)
Requires-Dist: xmler (==0.2.0)
Requires-Dist: certifi (==2022.6.15) ; python_full_version >= "3.6.0"
Requires-Dist: charset-normalizer (==2.1.0) ; python_full_version >= "3.6.0"
Requires-Dist: future (==0.18.2) ; python_version >= "2.6" and python_version not in "3.0, 3.1, 3.2, 3.3"
Requires-Dist: urllib3 (==1.26.10) ; python_version >= "2.7" and python_version not in "3.0, 3.1, 3.2, 3.3, 3.4, 3.5" and python_version < "4"
Requires-Dist: idna (==3.3) ; python_version >= "3.5"
Requires-Dist: pyqt5-sip (==12.11.0) ; python_version >= "3.7"
